<?xml version="1.0" encoding="utf-8"?>
<Session SID="2151" BitFlags="19">
  <SessionTimers ClientConnected="2017-08-07T15:15:46.7187922-05:00" ClientBeginRequest="2017-08-07T15:15:50.8100192-05:00" GotRequestHeaders="2017-08-07T15:15:50.8100192-05:00" ClientDoneRequest="2017-08-07T15:15:50.8100192-05:00" GatewayTime="0" DNSTime="0" TCPConnectTime="0" HTTPSHandshakeTime="0" ServerConnected="2017-08-07T15:15:50.7289949-05:00" FiddlerBeginRequest="2017-08-07T15:15:50.8110195-05:00" ServerGotRequest="2017-08-07T15:15:50.8110195-05:00" ServerBeginResponse="2017-08-07T15:15:51.2551527-05:00" GotResponseHeaders="2017-08-07T15:15:51.2551527-05:00" ServerDoneResponse="2017-08-07T15:15:51.2551527-05:00" ClientBeginResponse="2017-08-07T15:15:51.2551527-05:00" ClientDoneResponse="2017-08-07T15:15:51.2551527-05:00" />
  <PipeInfo CltReuse="true" Reused="true" />
  <SessionFlags>
    <SessionFlag N="x-clientport" V="64586" />
    <SessionFlag N="x-responsebodytransferlength" V="2,480" />
    <SessionFlag N="x-egressport" V="64587" />
    <SessionFlag N="x-hostip" V="10.16.0.63" />
    <SessionFlag N="x-processinfo" V="iexplore:8772" />
    <SessionFlag N="x-clientip" V="::ffff:127.0.0.1" />
    <SessionFlag N="x-serversocket" V="REUSE ServerPipe#2148" />
  </SessionFlags>
</Session>