<?xml version="1.0" encoding="utf-8"?>
<Session SID="393" BitFlags="2100">
  <SessionTimers ClientConnected="2017-08-07T13:44:39.5699441-05:00" ClientBeginRequest="2017-08-07T13:44:39.5799451-05:00" GotRequestHeaders="2017-08-07T13:44:39.5799451-05:00" ClientDoneRequest="2017-08-07T13:44:39.5799451-05:00" GatewayTime="0" DNSTime="4" TCPConnectTime="118" HTTPSHandshakeTime="331" ServerConnected="2017-08-07T13:44:39.7029574-05:00" FiddlerBeginRequest="2017-08-07T13:44:39.7029574-05:00" ServerGotRequest="2017-08-07T13:44:39.7029574-05:00" ServerBeginResponse="0001-01-01T00:00:00" GotResponseHeaders="0001-01-01T00:00:00" ServerDoneResponse="0001-01-01T00:00:00" ClientBeginResponse="2017-08-07T13:44:39.7029574-05:00" ClientDoneResponse="2017-08-07T13:44:39.7029574-05:00" />
  <PipeInfo />
  <TunnelInfo BytesEgress="0" BytesIngress="0" />
  <SessionFlags>
    <SessionFlag N="https-server-cipher" V="Aes128 128bits" />
    <SessionFlag N="x-responsebodytransferlength" V="0" />
    <SessionFlag N="https-server-version" V="Tls" />
    <SessionFlag N="https-client-snihostname" V="clientservices.googleapis.com" />
    <SessionFlag N="x-clientip" V="::ffff:127.0.0.1" />
    <SessionFlag N="x-clientport" V="55323" />
    <SessionFlag N="https-client-sessionid" V="25 D1 B6 AC 04 6C A6 E3 54 D6 F9 73 BA 55 AB DE D5 2A 64 BD EA 00 8F 75 0C 53 4C 2A 5A 20 33 DE" />
    <SessionFlag N="x-processinfo" V="chrome:14588" />
    <SessionFlag N="https-client-version" V="Tls" />
    <SessionFlag N="x-egressport" V="55324" />
    <SessionFlag N="x-hostip" V="172.217.1.35" />
  </SessionFlags>
</Session>